project_essential/hardware_modules/control_unit/output_signal.v
module output_signal(state, instruction_argument, datapath_output_signals);
    input[3:0] state;
    input[5:0] instruction_argument;

     // 14 signals for the datapath to handle 
     // - Done, Extern, AddSub, Gout, Gin, Ain, R3_out, R2_out, R1_out, R0_out, R3_in, R2_in, R1_in, R0_in,
    output reg[13:0] datapath_output_signals;

    wire[1:0] Rx = instruction_argument[5:4];
    wire[1:0] Ry = instruction_argument[3:2];
    // wire[3:0] data = instruction_argument[3:0];

    always @(*) begin
        datapath_output_signals = 14'b0; // RESET EVERYTHING

        case(state)
            4'd0: begin
            end

            4'd1: begin
                datapath_output_signals[Rx] = 1;
                datapath_output_signals[12] = 1;
                datapath_output_signals[13] = 1;
            end

            4'd2: begin
                datapath_output_signals[Rx+4] = 1;
                datapath_output_signals[8] = 1;
            end

            4'd3: begin
                datapath_output_signals[Ry] = 1;
                datapath_output_signals[9] = 1;
            end

            4'd4: begin
                datapath_output_signals[10] = 1;
                datapath_output_signals[Rx] = 1;
                datapath_output_signals[13] = 1;
            end

            4'd5: begin
                datapath_output_signals[Rx] = 1;
                datapath_output_signals[Ry+4] = 1;
                datapath_output_signals[13] = 1;
            end
        endcase
    end

endmodule

project_essential/hardware_modules/four_bit_register.v
module four_bit_register(clk, rst, D, Q); // D flip flop positive edge registers.
    input clk, rst;
    input[3:0] D;
    output reg[3:0] Q;

    always @(posedge clk or posedge rst) begin
        if (rst == 1'b1)
            Q <= 4'b0;
        else
            Q <= D; 
    end
endmodule

project_essential/hardware_modules/control_unit/next_state_cu.v
module next_state_cu(state, in, rst, n_state);
    input[3:0] state;
    input[1:0] in;
    input rst;
    output reg[3:0] n_state;

    wire[5:0] temp;
    assign temp = {state, in};

    always @(posedge rst) begin
        if (rst == 1'b1)
            n_state <= 4'b0000;
    end

    always @(temp) begin
        casez(temp)
            6'b000000 : begin n_state <= 4'b0001; end
            6'b000001 : begin n_state <= 4'b0101; end
            6'b000010 : begin n_state <= 4'b0010; end
            // 6'b000011 : begin n_state <= 4'b0010; end
            6'b0001?? : begin n_state <= 4'b0000; end
            6'b0010?? : begin n_state <= 4'b0011; end
            6'b0011?? : begin n_state <= 4'b0100; end
            6'b0100?? : begin n_state <= 4'b0000; end
            6'b0101?? : begin n_state <= 4'b0000; end

            default : begin n_state <= 4'b0000; end
        endcase
    end


endmodule

project_essential/hardware_modules/control_unit/control_unit.v
module control_unit(clk, rst, instruction, datapath_signals, immediate_data);
    input clk, rst;
    input[7:0] instruction; // 8bit instruction
    output[13:0] datapath_signals; //14 signals
    output[3:0] immediate_data;

    wire[1:0] operation_code = instruction[7:6]; // Extract Operation for State Transition
    wire[5:0] operation_arguments = instruction[5:0]; // 6bits of arguments
    assign immediate_data = instruction[3:0]; // Send to 4 bit external data register.

    wire[3:0] current_state_wire, next_state_wire; // Store in 4bit register

    next_state_cu next_state(.state(current_state_wire), .in(operation_code), .rst(rst), .n_state(next_state_wire));
    four_bit_register inst_reg(.clk(clk), .rst(rst), .D(next_state_wire), .Q(current_state_wire));
    output_signal output_signal(.state(curr_state_wire), .instruction_argument(operation_arguments), .datapath_output_signals(datapath_signals));
endmodule

project_essential/hardware_modules/control_unit/control_unit_tb.v
`timescale 1ns / 1ps

module control_unit_TB;

    reg clk, rst;
    reg[7:0] instruction;
    control_unit my_CU(.clk(clk), .rst(rst), .instruction(instruction));

    //Initialisations
    initial clk = 0;
    initial rst = 0;
    

    always #5 clk = ~clk; // Full clock period = 10ns = 100MHz

    // Dump VCD for GTKWave
    initial begin
        $dumpfile("control_unit_TB.vcd");
        $dumpvars(0, control_unit_TB);
	end


    integer i;

    initial begin 
        rst = 1;
        #10
        rst = 0;

        #10
        instruction = 8'b00001001; // LDI R0, 9
        #20
        instruction = 8'b01001000; // MOV R0, R2
        #20
        instruction = 8'b10110000; // ADD R1, R2
        #40

        #10 $finish;
    end

endmodule

project_essential/hardware_modules/control_unit/control_unit_TB.vcd
$date
	Mon May 18 16:35:30 2026
$end
$version
	Icarus Verilog
$end
$timescale
	1ps
$end
$scope module control_unit_TB $end
$var reg 1 ! clk $end
$var reg 8 " instruction [7:0] $end
$var reg 1 # rst $end
$scope module my_CU $end
$var wire 1 ! clk $end
$var wire 8 $ instruction [7:0] $end
$var wire 1 # rst $end
$var wire 2 % operation_code [1:0] $end
$var wire 6 & operation_arguments [5:0] $end
$var wire 4 ' next_state_wire [3:0] $end
$var wire 4 ( immediate_data [3:0] $end
$var wire 14 ) datapath_signals [13:0] $end
$var wire 4 * current_state_wire [3:0] $end
$scope module inst_reg $end
$var wire 1 ! clk $end
$var wire 1 # rst $end
$var wire 4 + D [3:0] $end
$var reg 4 , Q [3:0] $end
$upscope $end
$scope module next_state $end
$var wire 2 - in [1:0] $end
$var wire 1 # rst $end
$var wire 4 . state [3:0] $end
$var wire 6 / temp [5:0] $end
$var reg 4 0 n_state [3:0] $end
$upscope $end
$scope module output_signal $end
$var wire 6 1 instruction_argument [5:0] $end
$var wire 4 2 state [3:0] $end
$var wire 2 3 Ry [1:0] $end
$var wire 2 4 Rx [1:0] $end
$var reg 14 5 datapath_output_signals [13:0] $end
$upscope $end
$upscope $end
$upscope $end
$enddefinitions $end
$comment Show the parameter values. $end
$dumpall
$end
#0
$dumpvars
b0 5
bx 4
bx 3
b0 2
bx 1
b0 0
b0xx /
b0 .
bx -
b0 ,
b0 +
b0 *
b0 )
bx (
b0 '
bx &
bx %
bx $
1#
bx "
0!
$end
#5000
1!
#10000
0!
0#
#15000
1!
#20000
b1 '
b1 +
b1 0
b0 4
b10 3
b0 /
b0 %
b0 -
b1001 &
b1001 1
b1001 (
0!
b1001 "
b1001 $
#25000
b0 '
b0 +
b0 0
b11000000000001 )
b11000000000001 5
b100 /
b1 *
b1 ,
b1 .
b1 2
1!
#30000
0!
#35000
b1 '
b1 +
b1 0
b0 )
b0 5
b0 /
b0 *
b0 ,
b0 .
b0 2
1!
#40000
b101 '
b101 +
b101 0
b1 /
b1 %
b1 -
b1000 &
b1000 1
b1000 (
0!
b1001000 "
b1001000 $
#45000
b0 '
b0 +
b0 0
b10000001000001 )
b10000001000001 5
b10101 /
b101 *
b101 ,
b101 .
b101 2
1!
#50000
0!
#55000
b101 '
b101 +
b101 0
b0 )
b0 5
b1 /
b0 *
b0 ,
b0 .
b0 2
1!
#60000
b10 '
b10 +
b10 0
b11 4
b0 3
b10 /
b10 %
b10 -
b110000 &
b110000 1
b0 (
0!
b10110000 "
b10110000 $
#65000
b11 '
b11 +
b11 0
b110000000 )
b110000000 5
b1010 /
b10 *
b10 ,
b10 .
b10 2
1!
#70000
0!
#75000
b100 '
b100 +
b100 0
b1000000001 )
b1000000001 5
b1110 /
b11 *
b11 ,
b11 .
b11 2
1!
#80000
0!
#85000
b0 '
b0 +
b0 0
b10010000001000 )
b10010000001000 5
b10010 /
b100 *
b100 ,
b100 .
b100 2
1!
#90000
0!
#95000
b10 '
b10 +
b10 0
b0 )
b0 5
b10 /
b0 *
b0 ,
b0 .
b0 2
1!
#100000
0!
#105000
b11 '
b11 +
b11 0
b110000000 )
b110000000 5
b1010 /
b10 *
b10 ,
b10 .
b10 2
1!
