lab3/L3 P3/decoder_7seg.v
module decoder_7seg(code, decoded_output);

	input[1:0] code;
	output reg[6:0]  decoded_output;
	
 
	//either do with equations: 
	/*
	output[6:0]  decoded_output;
	assign decoded_output[0] = (code[1] & code[0]) | (~code[1] & ~code[0]);
	assign decoded_output[1] = (code[1] & code[0]) | (~code[1] & ~code[0]);
	assign decoded_output[2] = ...;
	*/
	
	// or with case statement:
	/*
	output reg[6:0]  decoded_output;
	always @(code) begin
		case (code)
		4'b0000 : begin decoded_output = 7'b???????; end
		...
		default : begin ... end
	endcase
	end
	*/
	
	always @(code) begin
		case (code)
		2'b00 : begin decoded_output = 7'b0000111; end
		2'b01 : begin decoded_output = 7'b1110000; end
		2'b10 : begin decoded_output = 7'b0011100; end
		default : begin decoded_output = 7'b1100011; end
	endcase
	end



 
endmodule

lab2/Templates/P1/one_bit_2to1mux.v
module one_bit_2to1mux (s,x,y,m);
 
	input s, x, y;
	output m;
	
	assign m = (~(s) & x) | (s & (y));
 
endmodule

lab2/Templates/P3/one_bit_4to1mux.v
module one_bit_4to1mux (s,u,v,w,x,m);
 
	input[1:0] s;
	input u,v,w,x;
	output m;
	
	wire t1, t2;
	
	
	one_bit_2to1mux mux1(.s(s[0]),.x(u),.y(v),.m(t1)); //complete
	//complete other instantiations

	one_bit_2to1mux mux2(.s(s[0]),.x(w),.y(x),.m(t2));

	one_bit_2to1mux mux3(.s(s[1]),.x(t1),.y(t2),.m(m));
	

 
endmodule

lab2/Templates/P3/two_bit_4to1mux.v
module two_bit_4to1mux (s,u,v,w,x,m);
 
	input[1:0] s;
	input[1:0] u, v, w, x;
	output[1:0] m;
	
	one_bit_4to1mux mux1(.s(s), .u(u[0]), .v(v[0]), .w(w[0]), .x(x[0]), .m(m[0])); //complete instantiation
	//complete other instantiations

	one_bit_4to1mux mux2(.s(s), .u(u[1]), .v(v[1]), .w(w[1]), .x(x[1]), .m(m[1]));



endmodule

lab3/L3 P2/lab3_P2.v
module lab3_P2 (s,u,v,w,x,chosen_7segCode);
 
	input[1:0] s;
	input[1:0] u, v, w, x;
	output[6:0] chosen_7segCode;
	
	wire[1:0] temp;
	
	/* need to connect an instance of two_bit_4to1mux or
	two_bit_4to1muxV2 (named part3) to an instance of decoder_7seg
	named part4. 
	
	Use the wire 2-bit called temp to connect them 
	(note output of two_bit_4to1mux is 2-bit, input to decoder_7seg is 
	2-bit)
	*/
	
	// Complete your choice of the following
	//two_bit_4to1mux part3(.s(),...);
	//two_bit_4to1muxV2 part3(.s(),...);
	//decoder_7seg part4(.code());

	two_bit_4to1mux part3(.s(s), .u(u), .v(v), .w(w), .x(x), .m(temp));

	decoder_7seg part4(.code(temp), .decoded_output(chosen_7segCode));



endmodule

lab3/L3 P2/lab3_P2_TB.v
`timescale 1ns / 1ps
 
module lab3_P2_TB;
 
	// ------------------ Instantiate module ------------------
	// We are instantiating the module mux2, naming it instantiate_mux2.
	// select, input1, input2 are controlled by the testbench, output is 
	// checked  within the testbench
 
	reg [3:0] count;
	reg [1:0] S,U,V,W,X;
	
	wire [6:0] output_7seg;
	lab3_P2 instantiate_p5 (.s(S),.u(U),.v(V),.w(W),
								.x(X),.chosen_7segCode(output_7seg));
 	
	initial begin 
		count = 4'b0000;
	end
	
	always begin
		#50
		count=count+4'b0001;
	end
	
	always @(count) begin
		case (count)
		4'b0000 : begin S = 2'b00; U = 2'b00; V = 2'b01; W = 2'b10; X = 2'b11; end
		4'b0001 : begin S = 2'b01; U = 2'b00; V = 2'b01; W = 2'b10; X = 2'b11; end
		default : begin S = 2'b11; U = 2'b00; V = 2'b01; W = 2'b10; X = 2'b11; end
	endcase
	end

	initial begin

        $dumpfile("lab3_P2_TB.vcd");
        $dumpvars(0, lab3_P2_TB);
        #1000 
        $finish;

	end

 
endmodule

lab3/L3 P2/lab3_P2_TB.vcd
$date
	Fri Mar 27 15:35:32 2026
$end
$version
	Icarus Verilog
$end
$timescale
	1ps
$end
$scope module lab3_P2_TB $end
$var wire 7 ! output_7seg [6:0] $end
$var reg 2 " S [1:0] $end
$var reg 2 # U [1:0] $end
$var reg 2 $ V [1:0] $end
$var reg 2 % W [1:0] $end
$var reg 2 & X [1:0] $end
$var reg 4 ' count [3:0] $end
$scope module instantiate_p5 $end
$var wire 2 ( s [1:0] $end
$var wire 2 ) u [1:0] $end
$var wire 2 * v [1:0] $end
$var wire 2 + w [1:0] $end
$var wire 2 , x [1:0] $end
$var wire 2 - temp [1:0] $end
$var wire 7 . chosen_7segCode [6:0] $end
$scope module part3 $end
$var wire 2 / s [1:0] $end
$var wire 2 0 u [1:0] $end
$var wire 2 1 v [1:0] $end
$var wire 2 2 w [1:0] $end
$var wire 2 3 x [1:0] $end
$var wire 2 4 m [1:0] $end
$scope module mux1 $end
$var wire 2 5 s [1:0] $end
$var wire 1 6 u $end
$var wire 1 7 v $end
$var wire 1 8 w $end
$var wire 1 9 x $end
$var wire 1 : t2 $end
$var wire 1 ; t1 $end
$var wire 1 < m $end
$scope module mux1 $end
$var wire 1 ; m $end
$var wire 1 = s $end
$var wire 1 6 x $end
$var wire 1 7 y $end
$upscope $end
$scope module mux2 $end
$var wire 1 : m $end
$var wire 1 > s $end
$var wire 1 8 x $end
$var wire 1 9 y $end
$upscope $end
$scope module mux3 $end
$var wire 1 < m $end
$var wire 1 ? s $end
$var wire 1 ; x $end
$var wire 1 : y $end
$upscope $end
$upscope $end
$scope module mux2 $end
$var wire 2 @ s [1:0] $end
$var wire 1 A u $end
$var wire 1 B v $end
$var wire 1 C w $end
$var wire 1 D x $end
$var wire 1 E t2 $end
$var wire 1 F t1 $end
$var wire 1 G m $end
$scope module mux1 $end
$var wire 1 F m $end
$var wire 1 H s $end
$var wire 1 A x $end
$var wire 1 B y $end
$upscope $end
$scope module mux2 $end
$var wire 1 E m $end
$var wire 1 I s $end
$var wire 1 C x $end
$var wire 1 D y $end
$upscope $end
$scope module mux3 $end
$var wire 1 G m $end
$var wire 1 J s $end
$var wire 1 F x $end
$var wire 1 E y $end
$upscope $end
$upscope $end
$upscope $end
$scope module part4 $end
$var wire 2 K code [1:0] $end
$var reg 7 L decoded_output [6:0] $end
$upscope $end
$upscope $end
$upscope $end
$enddefinitions $end
$comment Show the parameter values. $end
$dumpall
$end
#0
$dumpvars
b111 L
b0 K
0J
0I
0H
0G
0F
1E
1D
1C
0B
0A
b0 @
0?
0>
0=
0<
0;
0:
19
08
17
06
b0 5
b0 4
b11 3
b10 2
b1 1
b0 0
b0 /
b111 .
b0 -
b11 ,
b10 +
b1 *
b0 )
b0 (
b0 '
b11 &
b10 %
b1 $
b0 #
b0 "
b111 !
$end
#50000
b1110000 !
b1110000 .
b1110000 L
b1 -
b1 4
b1 K
1<
1;
1:
1=
1>
1H
1I
b1 "
b1 (
b1 /
b1 5
b1 @
b1 '
#100000
b1100011 !
b1100011 .
b1100011 L
b11 -
b11 4
b11 K
1G
1?
1J
b11 "
b11 (
b11 /
b11 5
b11 @
b10 '
#150000
b11 '
#200000
b100 '
#250000
b101 '
#300000
b110 '
#350000
b111 '
#400000
b1000 '
#450000
b1001 '
#500000
b1010 '
#550000
b1011 '
#600000
b1100 '
#650000
b1101 '
#700000
b1110 '
#750000
b1111 '
#800000
b111 !
b111 .
b111 L
0;
0:
0<
1E
b0 -
b0 4
b0 K
0G
0=
0>
0?
0H
0I
0J
b0 "
b0 (
b0 /
b0 5
b0 @
b0 '
#850000
b1110000 !
b1110000 .
b1110000 L
b1 -
b1 4
b1 K
1<
1;
1:
1=
1>
1H
1I
b1 "
b1 (
b1 /
b1 5
b1 @
b1 '
#900000
b1100011 !
b1100011 .
b1100011 L
b11 -
b11 4
b11 K
1G
1?
1J
b11 "
b11 (
b11 /
b11 5
b11 @
b10 '
#950000
b11 '
#1000000
b100 '
