lab2/Templates/P1/one_bit_2to1mux.v
module one_bit_2to1mux (s,x,y,m);
 
	input s, x, y;
	output m;
	
	assign m = (~(s) & x) | (s & (y));
 
endmodule

lab2/Templates/P1/one_bit_2to1mux_TB.v
`timescale 1ns / 1ps
 
module one_bit_2to1mux_TB;
 
	// ------------------ Instantiate module ------------------
	// We are instantiating the module mux2, naming it instantiate_mux2.
	// select, input1, input2 are controlled by the testbench, output is 
	// checked  within the testbench
 
	reg [3:0] count;
	reg select, input1, input2;
	wire output1;
	one_bit_2to1mux instantiate_mux2(.s(select),.x(input1),.y(input2),.m(output1));
 	
	initial begin 
		count = 4'b0000;
	end
	
	always begin
		#50
		count=count+4'b0001;
	end
	
	always @(count) begin
		case (count)
		4'b0000 : begin input1 = 1'b0; input2 = 1'b1; select = 1'b0; end
		4'b0001 : begin input1 = 1'b0; input2 = 1'b1; select = 1'b1; end
		4'b0010 : begin input1 = 1'b1; input2 = 1'b0; select = 1'b0; end 
		4'b0011 : begin input1 = 1'b1; input2 = 1'b0; select = 1'b1; end
		default : begin input1 = 1'b0; input2 = 1'b0; select = 1'b0; end
	endcase
	end

	// Dump VCD for GTKWave
    initial begin
        $dumpfile("one_bit_2to1mux_TB.vcd");
        $dumpvars(0, one_bit_2to1mux_TB);
        #1000 
        $finish;
	end



 
endmodule

lab2/Templates/P1/one_bit_2to1mux_TB.vcd
$date
	Fri Mar 27 11:27:21 2026
$end
$version
	Icarus Verilog
$end
$timescale
	1ps
$end
$scope module one_bit_2to1mux_TB $end
$var wire 1 ! output1 $end
$var reg 4 " count [3:0] $end
$var reg 1 # input1 $end
$var reg 1 $ input2 $end
$var reg 1 % select $end
$scope module instantiate_mux2 $end
$var wire 1 ! m $end
$var wire 1 % s $end
$var wire 1 # x $end
$var wire 1 $ y $end
$upscope $end
$upscope $end
$enddefinitions $end
$comment Show the parameter values. $end
$dumpall
$end
#0
$dumpvars
0%
1$
0#
b0 "
0!
$end
#50000
1!
1%
b1 "
#100000
1!
0%
0$
1#
b10 "
#150000
0!
1%
b11 "
#200000
0%
0#
b100 "
#250000
b101 "
#300000
b110 "
#350000
b111 "
#400000
b1000 "
#450000
b1001 "
#500000
b1010 "
#550000
b1011 "
#600000
b1100 "
#650000
b1101 "
#700000
b1110 "
#750000
b1111 "
#800000
1$
b0 "
#850000
1!
1%
b1 "
#900000
1!
0%
0$
1#
b10 "
#950000
0!
1%
b11 "
#1000000
0%
0#
b100 "
