lab2/Templates/P1/one_bit_2to1mux.v
module one_bit_2to1mux (s,x,y,m);
 
	input s, x, y;
	output m;
	
	assign m = (~(s) & x) | (s & (y));
 
endmodule

lab2/Templates/P1/four_bit_2to1mux.v
module four_bit_2to1mux (sel,a,b,chosen);
 
	input sel;
	input[3:0] a, b;
	output[3:0] chosen;
	
	//fill in wires to connect s,x,y, m with inputs and outputs sel, a, b, chosen
	one_bit_2to1mux mux1(.s(sel),.x(a[0]),.y(b[0]),.m(chosen[0])); 
	//Complete other instantiations
	one_bit_2to1mux mux2(.s(sel),.x(a[1]),.y(b[1]),.m(chosen[1])); 
	one_bit_2to1mux mux3(.s(sel),.x(a[2]),.y(b[2]),.m(chosen[2])); 
	one_bit_2to1mux mux4(.s(sel),.x(a[3]),.y(b[3]),.m(chosen[3])); 
 
endmodule

lab2/Templates/P1/part1_TB.v
`timescale 1ns / 1ps
 
module part1_TB;
 
	// ------------------ Instantiate module ------------------
	// We are instantiating the module mux2, naming it instantiate_mux2.
	// select, input1, input2 are controlled by the testbench, output is 
	// checked  within the testbench
 
	reg [3:0] count;
	reg select;
	reg [3:0] input1, input2;
	wire [3:0] output1;
	
	four_bit_2to1mux instantiate_mux4(.sel(select),.a(input1),.b(input2),.chosen(output1));
 	
	initial begin 
		count = 4'b0000;
	end
	
	always begin
		#50
		count=count+4'b0001;
	end
	
	always @(count) begin
		case (count)
		4'b0000 : begin input1 = 4'b0000; input2 = 4'b0001; select = 1'b0; end
		4'b0001 : begin input1 = 4'b0010; input2 = 4'b0011; select = 1'b1; end
		4'b0010 : begin input1 = 4'b0100; input2 = 4'b0111; select = 1'b0; end 
		4'b0011 : begin input1 = 4'b1000; input2 = 4'b1111; select = 1'b1; end
		default : begin input1 = 4'b0000; input2 = 4'b0000; select = 1'b0; end
	endcase
	end

	// Dump VCD for GTKWave
    initial begin
        $dumpfile("part1_TB.vcd");
        $dumpvars(0, part1_TB);
        #1000 
        $finish;
	end

 
endmodule

lab2/Templates/P1/part1_TB.vcd
$date
	Fri Mar 27 11:43:42 2026
$end
$version
	Icarus Verilog
$end
$timescale
	1ps
$end
$scope module part1_TB $end
$var wire 4 ! output1 [3:0] $end
$var reg 4 " count [3:0] $end
$var reg 4 # input1 [3:0] $end
$var reg 4 $ input2 [3:0] $end
$var reg 1 % select $end
$scope module instantiate_mux4 $end
$var wire 4 & a [3:0] $end
$var wire 4 ' b [3:0] $end
$var wire 1 % sel $end
$var wire 4 ( chosen [3:0] $end
$scope module mux1 $end
$var wire 1 ) m $end
$var wire 1 % s $end
$var wire 1 * x $end
$var wire 1 + y $end
$upscope $end
$scope module mux2 $end
$var wire 1 , m $end
$var wire 1 % s $end
$var wire 1 - x $end
$var wire 1 . y $end
$upscope $end
$scope module mux3 $end
$var wire 1 / m $end
$var wire 1 % s $end
$var wire 1 0 x $end
$var wire 1 1 y $end
$upscope $end
$scope module mux4 $end
$var wire 1 2 m $end
$var wire 1 % s $end
$var wire 1 3 x $end
$var wire 1 4 y $end
$upscope $end
$upscope $end
$upscope $end
$enddefinitions $end
$comment Show the parameter values. $end
$dumpall
$end
#0
$dumpvars
04
03
02
01
00
0/
0.
0-
0,
1+
0*
0)
b0 (
b1 '
b0 &
0%
b1 $
b0 #
b0 "
b0 !
$end
#50000
1)
b11 !
b11 (
1,
1.
1-
1%
b11 $
b11 '
b10 #
b10 &
b1 "
#100000
1/
0)
b100 !
b100 (
0,
11
0-
10
0%
b111 $
b111 '
b100 #
b100 &
b10 "
#150000
1)
1,
b1111 !
b1111 (
12
14
00
13
1%
b1111 $
b1111 '
b1000 #
b1000 &
b11 "
#200000
0)
0,
0/
b0 !
b0 (
02
0+
0.
01
04
03
0%
b0 $
b0 '
b0 #
b0 &
b100 "
#250000
b101 "
#300000
b110 "
#350000
b111 "
#400000
b1000 "
#450000
b1001 "
#500000
b1010 "
#550000
b1011 "
#600000
b1100 "
#650000
b1101 "
#700000
b1110 "
#750000
b1111 "
#800000
1+
b1 $
b1 '
b0 "
#850000
1)
b11 !
b11 (
1,
1.
1-
1%
b11 $
b11 '
b10 #
b10 &
b1 "
#900000
1/
0)
b100 !
b100 (
0,
11
0-
10
0%
b111 $
b111 '
b100 #
b100 &
b10 "
#950000
1)
1,
b1111 !
b1111 (
12
14
00
13
1%
b1111 $
b1111 '
b1000 #
b1000 &
b11 "
#1000000
0)
0,
0/
b0 !
b0 (
02
0+
0.
01
04
03
0%
b0 $
b0 '
b0 #
b0 &
b100 "
