project_essential/hardware_modules/processor/four_bit_tri_buf.v
module four_bit_tri_buf(en, in, out);
    input en;
    input[3:0] in;
    output reg[3:0] out;
    always @ (en or in) begin
        if (en)
            out <= in;
        else
            out <= 4'bz;
    end
endmodule

project_essential/hardware_modules/datapath/four_bit_register_en.v
module four_bit_register_en(clk, rst, en, D, Q); // D flip flop positive edge registers.
    input clk, rst, en;
    input[3:0] D;
    output reg[3:0] Q;

    always @(posedge clk or posedge rst) begin
        if (rst == 1'b1)
            Q <= 4'b0;
        else if (en == 1'b1)
            Q <= D;
    end
endmodule

project_essential/hardware_modules/processor/ALU.v
module ALU(A, B, addSub, result);
	input [3:0] A;
	input [3:0] B;
    input addSub;
    output reg [3:0] result;

    always @(*) begin
        case (addSub)
            1'b0 : begin result = A + B; end
            1'b1 : begin result = A - B; end
        endcase
    end
endmodule

project_essential/hardware_modules/processor/datapath.v
module datapath(clk, rst, datapath_signals, immediate_data, done);
    input clk, rst;
    input[3:0] immediate_data;
    input[13:0] datapath_signals;
    output done;

    
    wire extern, AddSub, G_out, G_en, A_en, R3_out, R2_out, R1_out, R0_out, R3_en, R2_en, R1_en, R0_en;
    assign {done, extern, AddSub, G_out, G_en, A_en, R3_out, R2_out, R1_out, R0_out, R3_en, R2_en, R1_en, R0_en} = datapath_signals;

    wire[3:0] four_bit_bus, R0_Q, R1_Q, R2_Q, R3_Q, ALU_arg1, ALU_result, G_Q;

    four_bit_tri_buf extern_data(.en(extern), .in(immediate_data), .out(four_bit_bus));

    four_bit_register_en R0(.clk(clk), .rst(rst), .en(R0_en), .D(four_bit_bus), .Q(R0_Q));
    four_bit_tri_buf R0_tri(.en(R0_out), .in(R0_Q), .out(four_bit_bus));

    four_bit_register_en R1(.clk(clk), .rst(rst), .en(R1_en), .D(four_bit_bus), .Q(R1_Q));
    four_bit_tri_buf R1_tri(.en(R1_out), .in(R1_Q), .out(four_bit_bus));

    four_bit_register_en R2(.clk(clk), .rst(rst), .en(R2_en), .D(four_bit_bus), .Q(R2_Q));
    four_bit_tri_buf R2_tri(.en(R2_out), .in(R2_Q), .out(four_bit_bus));

    four_bit_register_en R3(.clk(clk), .rst(rst), .en(R3_en), .D(four_bit_bus), .Q(R3_Q));
    four_bit_tri_buf R3_tri(.en(R3_out), .in(R3_Q), .out(four_bit_bus));

    four_bit_register_en A(.clk(clk), .rst(rst), .en(A_en), .D(four_bit_bus), .Q(ALU_arg1));
    ALU adder(.A(ALU_arg1), .B(four_bit_bus), .addSub(AddSub), .result(ALU_result));

    four_bit_register_en G(.clk(clk), .rst(rst), .en(G_en), .D(ALU_result), .Q(G_Q));
    four_bit_tri_buf G_tri(.en(G_out), .in(G_Q), .out(four_bit_bus));


endmodule

project_essential/hardware_modules/processor/output_signal.v
module output_signal(state, instruction_argument, datapath_output_signals);
    input[3:0] state;
    input[5:0] instruction_argument;

     // 14 signals for the datapath to handle 
     // - Done, Extern, AddSub, Gout, Gin, Ain, R3_out, R2_out, R1_out, R0_out, R3_in, R2_in, R1_in, R0_in,
    output reg[13:0] datapath_output_signals;

    wire[1:0] Rx = instruction_argument[5:4];
    wire[1:0] Ry = instruction_argument[3:2];
    // wire[3:0] data = instruction_argument[3:0];

    always @(*) begin
        datapath_output_signals = 14'b0; // RESET EVERYTHING

        case(state)
            4'd0: begin // RESTART
            end

            4'd1: begin // LOAD
                datapath_output_signals[Rx] = 1;
                datapath_output_signals[12] = 1;
                datapath_output_signals[13] = 1;
            end

            4'd2: begin // ADD1
                datapath_output_signals[Rx+4] = 1;
                datapath_output_signals[8] = 1;
            end

            4'd3: begin // ADD2
                datapath_output_signals[11] = 0; //AddSub = 0
                datapath_output_signals[Ry+4] = 1;
                datapath_output_signals[9] = 1;
            end

            4'd4: begin // ADD3
                datapath_output_signals[10] = 1;
                datapath_output_signals[Rx] = 1;
                datapath_output_signals[13] = 1;
            end

            4'd5: begin // MOVE
                datapath_output_signals[Rx] = 1;
                datapath_output_signals[Ry+4] = 1;
                datapath_output_signals[13] = 1;
            end

            4'd6: begin //SUB1
                datapath_output_signals[Rx+4] = 1;
                datapath_output_signals[8] = 1;
            end
 
            4'd7: begin //SUB2
                datapath_output_signals[11] = 1; //AddSub = 1
                datapath_output_signals[Ry+4] = 1;
                datapath_output_signals[9] = 1;
            end

            4'd8: begin //SUB3
                datapath_output_signals[10] = 1;
                datapath_output_signals[Rx] = 1;
                datapath_output_signals[13] = 1;
            end
        endcase
    end

endmodule

project_essential/hardware_modules/four_bit_register.v
module four_bit_register(clk, rst, D, Q); // D flip flop positive edge registers.
    input clk, rst;
    input[3:0] D;
    output reg[3:0] Q;

    always @(posedge clk or posedge rst) begin
        if (rst == 1'b1)
            Q <= 4'b0;
        else
            Q <= D; 
    end
endmodule

project_essential/hardware_modules/processor/next_state_cu.v
module next_state_cu(state, in, rst, n_state);
    input[3:0] state;
    input[1:0] in;
    input rst;
    output reg[3:0] n_state;

    wire[5:0] temp;
    assign temp = {state, in};

    always @(posedge rst) begin
        if (rst == 1'b1)
            n_state <= 4'b0000;
    end

    always @(temp) begin
        casez(temp)
            6'b000000 : begin n_state <= 4'b0001; end // go to LOAD
            6'b000001 : begin n_state <= 4'b0101; end // go to MOV
            6'b000010 : begin n_state <= 4'b0010; end // go to ADD1
            6'b000011 : begin n_state <= 4'b0110; end // RESTART -> SUB1
            6'b0001?? : begin n_state <= 4'b0000; end // LOAD -> RESTART
            6'b0010?? : begin n_state <= 4'b0011; end // go to ADD2
            6'b0011?? : begin n_state <= 4'b0100; end // go to ADD3
            6'b0100?? : begin n_state <= 4'b0000; end // go to RESTART
            6'b0101?? : begin n_state <= 4'b0000; end // MOV -> RESTART
            6'b0110?? : begin n_state <= 4'b0111; end // SUB1 -> SUB2
            6'b0111?? : begin n_state <= 4'b1000; end // SUB2 -> SUB3
            default : begin n_state <= 4'b0000; end // SUB3 -> RESTART
        endcase
    end


endmodule

project_essential/hardware_modules/processor/control_unit.v
module control_unit(clk, rst, instruction, datapath_signals, immediate_data);
    input clk, rst;
    input[7:0] instruction; // 8bit instruction
    output[13:0] datapath_signals; //14 signals
    output[3:0] immediate_data;

    wire[1:0] operation_code = instruction[7:6]; // Extract Operation for State Transition
    wire[5:0] operation_arguments = instruction[5:0]; // 6bits of arguments
    assign immediate_data = instruction[3:0]; // Send to 4 bit external data register.

    wire[3:0] current_state_wire, next_state_wire; // Store in 4bit register

    next_state_cu next_state(.state(current_state_wire), .in(operation_code), .rst(rst), .n_state(next_state_wire));
    four_bit_register inst_reg(.clk(clk), .rst(rst), .D(next_state_wire), .Q(current_state_wire));
    output_signal output_signal(.state(current_state_wire), .instruction_argument(operation_arguments), .datapath_output_signals(datapath_signals));
endmodule

project_essential/hardware_modules/processor/processor_top.v
module processor_top(clk, rst, instruction, done);
    input clk;
    input rst;
    input [7:0] instruction;

    wire[13:0] datapath_wires;
    wire[3:0] data_load;
    output done;

    control_unit CU(.clk(clk), .rst(rst), .instruction(instruction), .datapath_signals(datapath_wires), .immediate_data(data_load));
    datapath DP(.clk(clk), .rst(rst), .datapath_signals(datapath_wires), .immediate_data(data_load), .done(done));
endmodule

project_essential/hardware_modules/processor/processor_top_TB.v
`timescale 1ns / 1ps

module processor_top_TB;

    reg clk, rst;
    reg [7:0] instruction;
    wire done;

    // localparam LDI = 2'b00;
    // localparam MOVE = 2'b01;

    processor_top my_processor(
        .clk(clk),
        .rst(rst),
        .instruction(instruction),
        .done(done)
    );

    initial clk = 0;
    always #5 clk = ~clk;

    initial begin
        $dumpfile("processor_top_TB.vcd");
        $dumpvars(0, processor_top_TB);
    end

    initial begin
        rst = 1;
        #10
        rst = 0;

        // Give first instruction
        @(posedge clk)
        instruction = 8'b00000101; // LDI R0, 5
        
        @(negedge done)
        instruction = 8'b00010100; // LDI R1, 4
        
        @(negedge done)
        instruction = 8'b11000100; // SUB R0, R1 => R0 = 1

        @(negedge done)
        instruction = 8'b01100000; // MOV R2, R0 => R2 = 1

        @(negedge done)
        instruction = 8'b10100100; // ADD R2, R1 => R2 = 5

        @(negedge done)
        instruction = 8'b00110111; // LDI R3, 7 

        @(negedge done)
        instruction = 8'b10111000; // ADD R3, R2 => R3 = 7+5 = 12 = C


        #50 $finish;
    end

endmodule

project_essential/hardware_modules/processor/processor_top_TB.vcd
$date
	Fri May 22 17:41:16 2026
$end
$version
	Icarus Verilog
$end
$timescale
	1ps
$end
$scope module processor_top_TB $end
$var wire 1 ! done $end
$var reg 1 " clk $end
$var reg 8 # instruction [7:0] $end
$var reg 1 $ rst $end
$scope module my_processor $end
$var wire 1 " clk $end
$var wire 8 % instruction [7:0] $end
$var wire 1 $ rst $end
$var wire 1 ! done $end
$var wire 14 & datapath_wires [13:0] $end
$var wire 4 ' data_load [3:0] $end
$scope module CU $end
$var wire 1 " clk $end
$var wire 8 ( instruction [7:0] $end
$var wire 1 $ rst $end
$var wire 2 ) operation_code [1:0] $end
$var wire 6 * operation_arguments [5:0] $end
$var wire 4 + next_state_wire [3:0] $end
$var wire 4 , immediate_data [3:0] $end
$var wire 14 - datapath_signals [13:0] $end
$var wire 4 . current_state_wire [3:0] $end
$scope module inst_reg $end
$var wire 1 " clk $end
$var wire 1 $ rst $end
$var wire 4 / D [3:0] $end
$var reg 4 0 Q [3:0] $end
$upscope $end
$scope module next_state $end
$var wire 2 1 in [1:0] $end
$var wire 1 $ rst $end
$var wire 4 2 state [3:0] $end
$var wire 6 3 temp [5:0] $end
$var reg 4 4 n_state [3:0] $end
$upscope $end
$scope module output_signal $end
$var wire 6 5 instruction_argument [5:0] $end
$var wire 4 6 state [3:0] $end
$var wire 2 7 Ry [1:0] $end
$var wire 2 8 Rx [1:0] $end
$var reg 14 9 datapath_output_signals [13:0] $end
$upscope $end
$upscope $end
$scope module DP $end
$var wire 1 " clk $end
$var wire 14 : datapath_signals [13:0] $end
$var wire 4 ; four_bit_bus [3:0] $end
$var wire 4 < immediate_data [3:0] $end
$var wire 1 $ rst $end
$var wire 1 = extern $end
$var wire 1 ! done $end
$var wire 1 > R3_out $end
$var wire 1 ? R3_en $end
$var wire 4 @ R3_Q [3:0] $end
$var wire 1 A R2_out $end
$var wire 1 B R2_en $end
$var wire 4 C R2_Q [3:0] $end
$var wire 1 D R1_out $end
$var wire 1 E R1_en $end
$var wire 4 F R1_Q [3:0] $end
$var wire 1 G R0_out $end
$var wire 1 H R0_en $end
$var wire 4 I R0_Q [3:0] $end
$var wire 1 J G_out $end
$var wire 1 K G_en $end
$var wire 4 L G_Q [3:0] $end
$var wire 1 M AddSub $end
$var wire 1 N A_en $end
$var wire 4 O ALU_result [3:0] $end
$var wire 4 P ALU_arg1 [3:0] $end
$scope module A $end
$var wire 4 Q D [3:0] $end
$var wire 1 " clk $end
$var wire 1 N en $end
$var wire 1 $ rst $end
$var reg 4 R Q [3:0] $end
$upscope $end
$scope module G $end
$var wire 1 " clk $end
$var wire 1 K en $end
$var wire 1 $ rst $end
$var wire 4 S D [3:0] $end
$var reg 4 T Q [3:0] $end
$upscope $end
$scope module G_tri $end
$var wire 1 J en $end
$var wire 4 U in [3:0] $end
$var reg 4 V out [3:0] $end
$upscope $end
$scope module R0 $end
$var wire 4 W D [3:0] $end
$var wire 1 " clk $end
$var wire 1 H en $end
$var wire 1 $ rst $end
$var reg 4 X Q [3:0] $end
$upscope $end
$scope module R0_tri $end
$var wire 1 G en $end
$var wire 4 Y in [3:0] $end
$var reg 4 Z out [3:0] $end
$upscope $end
$scope module R1 $end
$var wire 4 [ D [3:0] $end
$var wire 1 " clk $end
$var wire 1 E en $end
$var wire 1 $ rst $end
$var reg 4 \ Q [3:0] $end
$upscope $end
$scope module R1_tri $end
$var wire 1 D en $end
$var wire 4 ] in [3:0] $end
$var reg 4 ^ out [3:0] $end
$upscope $end
$scope module R2 $end
$var wire 4 _ D [3:0] $end
$var wire 1 " clk $end
$var wire 1 B en $end
$var wire 1 $ rst $end
$var reg 4 ` Q [3:0] $end
$upscope $end
$scope module R2_tri $end
$var wire 1 A en $end
$var wire 4 a in [3:0] $end
$var reg 4 b out [3:0] $end
$upscope $end
$scope module R3 $end
$var wire 4 c D [3:0] $end
$var wire 1 " clk $end
$var wire 1 ? en $end
$var wire 1 $ rst $end
$var reg 4 d Q [3:0] $end
$upscope $end
$scope module R3_tri $end
$var wire 1 > en $end
$var wire 4 e in [3:0] $end
$var reg 4 f out [3:0] $end
$upscope $end
$scope module adder $end
$var wire 4 g A [3:0] $end
$var wire 4 h B [3:0] $end
$var wire 1 M addSub $end
$var reg 4 i result [3:0] $end
$upscope $end
$scope module extern_data $end
$var wire 1 = en $end
$var wire 4 j in [3:0] $end
$var reg 4 k out [3:0] $end
$upscope $end
$upscope $end
$upscope $end
$upscope $end
$enddefinitions $end
$comment Show the parameter values. $end
$dumpall
$end
#0
$dumpvars
bz k
bx j
bx i
bz h
b0 g
bz f
b0 e
b0 d
bz c
bz b
b0 a
b0 `
bz _
bz ^
b0 ]
b0 \
bz [
bz Z
b0 Y
b0 X
bz W
bz V
b0 U
b0 T
bx S
b0 R
bz Q
b0 P
bx O
0N
0M
b0 L
0K
0J
b0 I
0H
0G
b0 F
0E
0D
b0 C
0B
0A
b0 @
0?
0>
0=
bx <
bz ;
b0 :
b0 9
bx 8
bx 7
b0 6
bx 5
b0 4
b0xx 3
b0 2
bx 1
b0 0
b0 /
b0 .
b0 -
bx ,
b0 +
bx *
bx )
bx (
bx '
b0 &
bx %
1$
bx #
0"
0!
$end
#5000
1"
#10000
0"
0$
#15000
b1 +
b1 /
b1 4
b0 8
b1 7
b0 3
b0 )
b0 1
b101 *
b101 5
b101 '
b101 ,
b101 <
b101 j
b101 #
b101 %
b101 (
1"
#20000
0"
#25000
b101 O
b101 S
b101 i
b101 ;
b101 Q
b101 W
b101 [
b101 _
b101 c
b101 h
b101 k
b0 +
b0 /
b0 4
1!
1=
1H
b11000000000001 &
b11000000000001 -
b11000000000001 9
b11000000000001 :
b100 3
b1 .
b1 0
b1 2
b1 6
1"
#30000
0"
#35000
bx O
bx S
bx i
bz ;
bz Q
bz W
bz [
bz _
bz c
bz h
bz k
b1 +
b1 /
b1 4
b1 8
b10100 *
b10100 5
b100 '
b100 ,
b100 <
b100 j
b10100 #
b10100 %
b10100 (
0!
0=
0H
b0 &
b0 -
b0 9
b0 :
b0 3
b0 .
b0 0
b0 2
b0 6
b101 I
b101 X
b101 Y
1"
#40000
0"
#45000
b100 O
b100 S
b100 i
b100 ;
b100 Q
b100 W
b100 [
b100 _
b100 c
b100 h
b100 k
b0 +
b0 /
b0 4
1!
1=
1E
b11000000000010 &
b11000000000010 -
b11000000000010 9
b11000000000010 :
b100 3
b1 .
b1 0
b1 2
b1 6
1"
#50000
0"
#55000
bx O
bx S
bx i
bz ;
bz Q
bz W
bz [
bz _
bz c
bz h
bz k
b110 +
b110 /
b110 4
b0 8
b11 )
b11 1
b100 *
b100 5
b11000100 #
b11000100 %
b11000100 (
0!
0=
0E
b0 &
b0 -
b0 9
b0 :
b11 3
b0 .
b0 0
b0 2
b0 6
b100 F
b100 \
b100 ]
1"
#60000
0"
#65000
b101 O
b101 S
b101 i
b101 ;
b101 Q
b101 W
b101 [
b101 _
b101 c
b101 h
b101 Z
b111 +
b111 /
b111 4
1N
1G
b100010000 &
b100010000 -
b100010000 9
b100010000 :
b11011 3
b110 .
b110 0
b110 2
b110 6
1"
#70000
0"
#75000
b100 ^
b100 ;
b100 Q
b100 W
b100 [
b100 _
b100 c
b100 h
bz Z
b1000 +
b1000 /
b1000 4
1K
1D
1M
0N
0G
b101000100000 &
b101000100000 -
b101000100000 9
b101000100000 :
b1 O
b1 S
b1 i
b11111 3
b111 .
b111 0
b111 2
b111 6
b101 P
b101 R
b101 g
1"
#80000
0"
#85000
b1 V
b1 ;
b1 Q
b1 W
b1 [
b1 _
b1 c
b1 h
bz ^
b0 +
b0 /
b0 4
b110 O
b110 S
b110 i
1!
1H
1J
0M
0K
0D
b10010000000001 &
b10010000000001 -
b10010000000001 9
b10010000000001 :
b1 L
b1 T
b1 U
b100011 3
b1000 .
b1000 0
b1000 2
b1000 6
1"
#90000
0"
#95000
bx O
bx S
bx i
bz ;
bz Q
bz W
bz [
bz _
bz c
bz h
bz V
b101 +
b101 /
b101 4
b10 8
b0 7
b1 )
b1 1
b100000 *
b100000 5
b0 '
b0 ,
b0 <
b0 j
b1100000 #
b1100000 %
b1100000 (
0!
0J
0H
b0 &
b0 -
b0 9
b0 :
b1 3
b0 .
b0 0
b0 2
b0 6
b1 I
b1 X
b1 Y
1"
#100000
0"
#105000
b110 O
b110 S
b110 i
b1 ;
b1 Q
b1 W
b1 [
b1 _
b1 c
b1 h
b1 Z
b0 +
b0 /
b0 4
1!
1G
1B
b10000000010100 &
b10000000010100 -
b10000000010100 9
b10000000010100 :
b10101 3
b101 .
b101 0
b101 2
b101 6
1"
#110000
0"
#115000
bx O
bx S
bx i
bz ;
bz Q
bz W
bz [
bz _
bz c
bz h
bz Z
b10 +
b10 /
b10 4
b1 7
b10 )
b10 1
b100100 *
b100100 5
b100 '
b100 ,
b100 <
b100 j
b10100100 #
b10100100 %
b10100100 (
0!
0G
0B
b0 &
b0 -
b0 9
b0 :
b10 3
b0 .
b0 0
b0 2
b0 6
b1 C
b1 `
b1 a
1"
#120000
0"
#125000
b110 O
b110 S
b110 i
b1 ;
b1 Q
b1 W
b1 [
b1 _
b1 c
b1 h
b1 b
b11 +
b11 /
b11 4
1N
1A
b101000000 &
b101000000 -
b101000000 9
b101000000 :
b1010 3
b10 .
b10 0
b10 2
b10 6
1"
#130000
0"
#135000
b100 ^
b100 ;
b100 Q
b100 W
b100 [
b100 _
b100 c
b100 h
bz b
b100 +
b100 /
b100 4
1K
1D
0N
0A
b1000100000 &
b1000100000 -
b1000100000 9
b1000100000 :
b101 O
b101 S
b101 i
b1110 3
b11 .
b11 0
b11 2
b11 6
b1 P
b1 R
b1 g
1"
#140000
0"
#145000
b110 O
b110 S
b110 i
b101 V
b101 ;
b101 Q
b101 W
b101 [
b101 _
b101 c
b101 h
bz ^
b0 +
b0 /
b0 4
1!
1B
1J
0K
0D
b10010000000100 &
b10010000000100 -
b10010000000100 9
b10010000000100 :
b101 L
b101 T
b101 U
b10010 3
b100 .
b100 0
b100 2
b100 6
1"
#150000
0"
#155000
bx O
bx S
bx i
bz ;
bz Q
bz W
bz [
bz _
bz c
bz h
bz V
b1 +
b1 /
b1 4
b11 8
b0 )
b0 1
b110111 *
b110111 5
b111 '
b111 ,
b111 <
b111 j
b110111 #
b110111 %
b110111 (
0!
0J
0B
b0 &
b0 -
b0 9
b0 :
b0 3
b0 .
b0 0
b0 2
b0 6
b101 C
b101 `
b101 a
1"
#160000
0"
#165000
b1000 O
b1000 S
b1000 i
b111 ;
b111 Q
b111 W
b111 [
b111 _
b111 c
b111 h
b111 k
b0 +
b0 /
b0 4
1!
1=
1?
b11000000001000 &
b11000000001000 -
b11000000001000 9
b11000000001000 :
b100 3
b1 .
b1 0
b1 2
b1 6
1"
#170000
0"
#175000
bx O
bx S
bx i
bz ;
bz Q
bz W
bz [
bz _
bz c
bz h
bz k
b10 +
b10 /
b10 4
b10 7
b10 )
b10 1
b111000 *
b111000 5
b1000 '
b1000 ,
b1000 <
b1000 j
b10111000 #
b10111000 %
b10111000 (
0!
0=
0?
b0 &
b0 -
b0 9
b0 :
b10 3
b0 .
b0 0
b0 2
b0 6
b111 @
b111 d
b111 e
1"
#180000
0"
#185000
b1000 O
b1000 S
b1000 i
b111 ;
b111 Q
b111 W
b111 [
b111 _
b111 c
b111 h
b111 f
b11 +
b11 /
b11 4
1N
1>
b110000000 &
b110000000 -
b110000000 9
b110000000 :
b1010 3
b10 .
b10 0
b10 2
b10 6
1"
#190000
0"
#195000
b101 b
b101 ;
b101 Q
b101 W
b101 [
b101 _
b101 c
b101 h
bz f
b100 +
b100 /
b100 4
1K
1A
0N
0>
b1001000000 &
b1001000000 -
b1001000000 9
b1001000000 :
b1100 O
b1100 S
b1100 i
b1110 3
b11 .
b11 0
b11 2
b11 6
b111 P
b111 R
b111 g
1"
#200000
0"
#205000
b11 O
b11 S
b11 i
b1100 V
b1100 ;
b1100 Q
b1100 W
b1100 [
b1100 _
b1100 c
b1100 h
bz b
b0 +
b0 /
b0 4
1!
1?
1J
0K
0A
b10010000001000 &
b10010000001000 -
b10010000001000 9
b10010000001000 :
b1100 L
b1100 T
b1100 U
b10010 3
b100 .
b100 0
b100 2
b100 6
1"
#210000
0"
#215000
bx O
bx S
bx i
bz ;
bz Q
bz W
bz [
bz _
bz c
bz h
bz V
b10 +
b10 /
b10 4
0!
0J
0?
b0 &
b0 -
b0 9
b0 :
b10 3
b0 .
b0 0
b0 2
b0 6
b1100 @
b1100 d
b1100 e
1"
#220000
0"
#225000
b11 O
b11 S
b11 i
b1100 ;
b1100 Q
b1100 W
b1100 [
b1100 _
b1100 c
b1100 h
b1100 f
b11 +
b11 /
b11 4
1N
1>
b110000000 &
b110000000 -
b110000000 9
b110000000 :
b1010 3
b10 .
b10 0
b10 2
b10 6
1"
