lab1/Q1/labtest_q1_hardware.v
module labtest_q1_hardware(a,b,c,x,y);
    input a,b,c;
    output reg x,y;
    
    wire[2:0] temp; //this is an optional wire you may/may not wish to use
    
    // complete the rest of the code
     assign temp = {a, b, c}; // 3-bit wire
     
     always @(temp) begin
        case (temp)
            3'b000       : begin x = 1'b1 ; y = 1'b0; end 
            3'b001       : begin x = 1'b0 ; y = 1'b0; end 
            3'b010       : begin x = 1'b0 ; y = 1'b0; end 
            3'b011       : begin x = 1'b0 ; y = 1'b1; end 
            3'b100       : begin x = 1'b0 ; y = 1'b0; end 
            3'b101       : begin x = 1'b1 ; y = 1'b0; end 
            3'b110       : begin x = 1'b0 ; y = 1'b1; end 
            3'b111       : begin x = 1'b0 ; y = 1'b0; end 
            default     : begin x = 1'b0 ; y = 1'b0; end 
        endcase
    end

endmodule

lab1/Q1/testbench_labtest_combinational.v
`timescale 1ns / 1ps
 
module testbench_labtest_combinational;
    
    // ------------------ Specify variables generated by testbench ------------------ 
    reg in1, in2, in3;
    
    // ------------------ Specify variables that are watched by testbench ------------------ 
    wire out1, out2;
    
    // Instantiate hardware Device Under Test (dut)
    labtest_q1_hardware dut(.a(in1),.b(in2),.c(in3), .x(out1),.y(out2));
 
    // ------------------ Setup inputs ------------------
    // Provide initial values for inputs. The ‘initial’ command
    // is only valid within the testbench.
    // Can use this for all simple testbenches

    integer count;
    initial begin 
        count = 0;
    end
 
    always begin
        #50
        count=count+1;
    end
 
    // Toggle inputs at different rates to cover all input  
    always @(count) begin
        case (count)
            0 : begin {in1, in2, in3} = 3'b000; end
            1 : begin {in1, in2, in3} = 3'b001; end
            2 : begin {in1, in2, in3} = 3'b010; end
            3 : begin {in1, in2, in3} = 3'b011; end
            4 : begin {in1, in2, in3} = 3'b100; end
            5 : begin {in1, in2, in3} = 3'b101; end
            6 : begin {in1, in2, in3} = 3'b110; end
            7 : begin {in1, in2, in3} = 3'b111; end
            default : begin {in1, in2, in3} = count[2:0];end 
        endcase
    end

    // Dump VCD for GTKWave
    initial begin
        $dumpfile("testbench_labtest_combinational.vcd");
        $dumpvars(0, testbench_labtest_combinational);
        #1000 
        $finish;
	end
 
endmodule

lab1/Q1/testbench_labtest_combinational.vcd
$date
	Fri Mar 20 13:10:08 2026
$end
$version
	Icarus Verilog
$end
$timescale
	1ps
$end
$scope module testbench_labtest_combinational $end
$var wire 1 ! out2 $end
$var wire 1 " out1 $end
$var reg 1 # in1 $end
$var reg 1 $ in2 $end
$var reg 1 % in3 $end
$var integer 32 & count [31:0] $end
$scope module dut $end
$var wire 1 # a $end
$var wire 1 $ b $end
$var wire 1 % c $end
$var wire 3 ' temp [2:0] $end
$var reg 1 " x $end
$var reg 1 ! y $end
$upscope $end
$upscope $end
$enddefinitions $end
$comment Show the parameter values. $end
$dumpall
$end
#0
$dumpvars
b0 '
b0 &
0%
0$
0#
1"
0!
$end
#50000
0"
b1 '
1%
b1 &
#100000
1$
b10 '
0%
b10 &
#150000
1!
b11 '
1%
b11 &
#200000
0!
1#
0$
b100 '
0%
b100 &
#250000
1"
b101 '
1%
b101 &
#300000
1!
0"
1$
b110 '
0%
b110 &
#350000
0!
b111 '
1%
b111 &
#400000
1"
0#
0$
b0 '
0%
b1000 &
#450000
0"
b1 '
1%
b1001 &
#500000
1$
b10 '
0%
b1010 &
#550000
1!
b11 '
1%
b1011 &
#600000
0!
1#
0$
b100 '
0%
b1100 &
#650000
1"
b101 '
1%
b1101 &
#700000
1!
0"
1$
b110 '
0%
b1110 &
#750000
0!
b111 '
1%
b1111 &
#800000
1"
0#
0$
b0 '
0%
b10000 &
#850000
0"
b1 '
1%
b10001 &
#900000
1$
b10 '
0%
b10010 &
#950000
1!
b11 '
1%
b10011 &
#1000000
0!
1#
0$
b100 '
0%
b10100 &
