lab5/Part2/output_signal.v
module output_signal(state, detected);

    input [3:0] state;
    output reg detected;

    always @(state) begin
        case (state)
            4'b0100: begin detected = 1'b1; end
            4'b1000: begin detected = 1'b1; end
            default: begin detected = 1'b0; end
        endcase
    end

endmodule

lab5/Part2/register.v
module register(clk, rst, D, Q); // D flip flop positive edge registers.
    input clk, rst;
    input[3:0] D;
    output reg[3:0] Q;

    always @(posedge clk or posedge rst) begin
        if (rst == 1'b1)
            Q <= 4'b0;
        else
            Q <= D; 
    end
endmodule

lab5/Part2/n_state.v
module n_state(state, w, rst, next_state);
    input [3:0] state;
    input w, rst;
    output reg [3:0] next_state;
    wire[4:0] temp;
    
    assign temp = {state, w};

    always @(posedge rst) begin
        if (rst == 1'b1)
            next_state <= 4'b0000;
    end

    always @(temp) begin
    case (temp)
        5'b00000 : begin next_state <= 4'b0001; end
        5'b00001 : begin next_state <= 4'b0101; end
        5'b00010 : begin next_state <= 4'b0010; end
        5'b00011 : begin next_state <= 4'b0101; end
        5'b00100 : begin next_state <= 4'b0011; end
        5'b00101 : begin next_state <= 4'b0101; end
        5'b00110 : begin next_state <= 4'b0100; end
        5'b00111 : begin next_state <= 4'b0101; end
        5'b01000 : begin next_state <= 4'b0100; end
        5'b01001 : begin next_state <= 4'b0101; end
        5'b01010 : begin next_state <= 4'b0001; end
        5'b01011 : begin next_state <= 4'b0110; end
        5'b01100 : begin next_state <= 4'b0001; end
        5'b01101 : begin next_state <= 4'b0111; end
        5'b01110 : begin next_state <= 4'b0001; end
        5'b01111 : begin next_state <= 4'b1000; end
        5'b10000 : begin next_state <= 4'b0001; end
        // 5'b10001 : begin next_state <= 4'b1000 end
        default : begin next_state <= 4'b1000; end
    endcase
    end
endmodule

lab5/Part2/seq_detector.v
module seq_detector(clk, rst, in, detected);
    input clk, rst, in;
    output detected;
    wire[3:0] next_state_wire, curr_state_wire;

    n_state n_state(.state(curr_state_wire), .w(in), .next_state(next_state_wire));
    register inst_reg(.D(next_state_wire), .clk(clk), .rst(rst), .Q(curr_state_wire));
    output_signal signal(.state(curr_state_wire), .detected(detected));

endmodule

lab5/Part2/seq_detected_TB.v
`timescale 1ns/1ps

module seq_detector_TB;

    reg clk, rst, in;
    wire detected;
    seq_detector my_detector(.clk(clk), .rst(rst), .in(in), .detected(detected));

    // Clock generation 
    initial clk = 0;
    initial in = 0;
    initial rst = 0;

    always #5 clk = ~clk; // Full clock period = 10ns = 100MHz

        // Dump VCD for GTKWave
    initial begin
        $dumpfile("seq_detector_TB.vcd");
        $dumpvars(0, seq_detector_TB);
	end


    // Input sequence
    reg [15:0] pattern = 16'b0101000010111110;
    integer i;

    initial begin 
        rst = 1;
        #10
        rst = 0;

        for (i = 15; i >= 0; i = i - 1) begin
            @(posedge clk); // wait for pos clock edge
            in = pattern[i];
        end

        #20 $finish;
    end



    // Dump VCD for GTKWave
    initial begin
        $dumpfile("seq_detector_TB.vcd");
        $dumpvars(0, seq_detector_TB);
        #1000 
        $finish;
	end


endmodule

lab5/Part2/seq_detector_TB.vcd
$date
	Sun May 17 23:15:07 2026
$end
$version
	Icarus Verilog
$end
$timescale
	1ps
$end
$scope module seq_detector_TB $end
$var wire 1 ! detected $end
$var reg 1 " clk $end
$var reg 1 # in $end
$var reg 16 $ pattern [15:0] $end
$var reg 1 % rst $end
$var integer 32 & i [31:0] $end
$scope module my_detector $end
$var wire 1 " clk $end
$var wire 1 # in $end
$var wire 1 % rst $end
$var wire 4 ' next_state_wire [3:0] $end
$var wire 1 ! detected $end
$var wire 4 ( curr_state_wire [3:0] $end
$scope module inst_reg $end
$var wire 1 " clk $end
$var wire 1 % rst $end
$var wire 4 ) D [3:0] $end
$var reg 4 * Q [3:0] $end
$upscope $end
$scope module n_state $end
$var wire 1 + rst $end
$var wire 4 , state [3:0] $end
$var wire 1 # w $end
$var wire 5 - temp [4:0] $end
$var reg 4 . next_state [3:0] $end
$upscope $end
$scope module signal $end
$var wire 4 / state [3:0] $end
$var reg 1 ! detected $end
$upscope $end
$upscope $end
$upscope $end
$scope module seq_detector_TB $end
$scope module my_detector $end
$scope module inst_reg $end
$upscope $end
$scope module n_state $end
$upscope $end
$scope module signal $end
$upscope $end
$upscope $end
$upscope $end
$enddefinitions $end
$comment Show the parameter values. $end
$dumpall
$end
#0
$dumpvars
b0 /
b1 .
b0 -
b0 ,
z+
b0 *
b1 )
b0 (
b1 '
bx &
1%
b101000010111110 $
0#
0"
0!
$end
#5000
1"
#10000
0"
b1111 &
0%
#15000
b10 '
b10 )
b10 .
b10 -
b1 (
b1 *
b1 ,
b1 /
b1110 &
1"
#20000
0"
#25000
b101 '
b101 )
b101 .
b10 (
b10 *
b10 ,
b10 /
b1101 &
b101 -
1#
1"
#30000
0"
#35000
b1 '
b1 )
b1 .
b101 (
b101 *
b101 ,
b101 /
b1100 &
b1010 -
0#
1"
#40000
0"
#45000
b101 '
b101 )
b101 .
b1 (
b1 *
b1 ,
b1 /
b1011 &
b11 -
1#
1"
#50000
0"
#55000
b1 '
b1 )
b1 .
b101 (
b101 *
b101 ,
b101 /
b1010 &
b1010 -
0#
1"
#60000
0"
#65000
b10 '
b10 )
b10 .
b10 -
b1 (
b1 *
b1 ,
b1 /
b1001 &
1"
#70000
0"
#75000
b11 '
b11 )
b11 .
b100 -
b10 (
b10 *
b10 ,
b10 /
b1000 &
1"
#80000
0"
#85000
b100 '
b100 )
b100 .
b110 -
b11 (
b11 *
b11 ,
b11 /
b111 &
1"
#90000
0"
#95000
1!
b101 '
b101 )
b101 .
b100 (
b100 *
b100 ,
b100 /
b110 &
b1001 -
1#
1"
#100000
0"
#105000
0!
b1 '
b1 )
b1 .
b101 (
b101 *
b101 ,
b101 /
b101 &
b1010 -
0#
1"
#110000
0"
#115000
b101 '
b101 )
b101 .
b1 (
b1 *
b1 ,
b1 /
b100 &
b11 -
1#
1"
#120000
0"
#125000
b110 '
b110 )
b110 .
b1011 -
b101 (
b101 *
b101 ,
b101 /
b11 &
1"
#130000
0"
#135000
b111 '
b111 )
b111 .
b1101 -
b110 (
b110 *
b110 ,
b110 /
b10 &
1"
#140000
0"
#145000
b1000 '
b1000 )
b1000 .
b1111 -
b111 (
b111 *
b111 ,
b111 /
b1 &
1"
#150000
0"
#155000
1!
b10001 -
b1000 (
b1000 *
b1000 ,
b1000 /
b0 &
1"
#160000
0"
#165000
b1 '
b1 )
b1 .
b11111111111111111111111111111111 &
b10000 -
0#
1"
#170000
0"
#175000
b10 '
b10 )
b10 .
0!
b10 -
b1 (
b1 *
b1 ,
b1 /
1"
#180000
0"
#185000
b11 '
b11 )
b11 .
b100 -
b10 (
b10 *
b10 ,
b10 /
1"
