project_essential/hardware_modules/register/register.v
module register(clk, rst, D, Q); // D flip flop positive edge registers.
    input clk, rst;
    input D;
    output reg Q;

    always @(posedge clk or posedge rst) begin
        if (rst == 1'b1)
            Q <= 1'b0;
        else
            Q <= D; 
    end
endmodule

project_essential/hardware_modules/register/register_TB.v
`timescale 1ns / 1ps // So #50 = 50ns

module register_TB;
    reg clk, rst, D;
    wire Q;

    register register(
        .clk(clk),
        .rst(rst),
        .D(D),
        .Q(Q)
    );

    initial clk = 1'b0;
    initial rst = 1'b1;
    initial D = 1'b0;

    //clock generation
    always #5 clk = ~clk;

    // Dump VCD for GTKWave
    initial begin
        $dumpfile("register_TB.vcd");
        $dumpvars(0, register_TB);
	end

    reg[7:0] D_sequence_input = 8'b00001111;
    integer i;
    initial begin
        #10
        rst = 0;

        for (i = 7; i >= 0; i = i - 1) begin
            @(posedge clk); // wait for pos clock edge
            D = D_sequence_input[i];
        end

        #20 $finish;
    end 



endmodule

project_essential/hardware_modules/register/register_TB.vcd
$date
	Sun May 17 23:47:37 2026
$end
$version
	Icarus Verilog
$end
$timescale
	1ps
$end
$scope module register_TB $end
$var wire 1 ! Q $end
$var reg 1 " D $end
$var reg 8 # D_sequence_input [7:0] $end
$var reg 1 $ clk $end
$var reg 1 % rst $end
$var integer 32 & i [31:0] $end
$scope module register $end
$var wire 1 " D $end
$var wire 1 $ clk $end
$var wire 1 % rst $end
$var reg 1 ! Q $end
$upscope $end
$upscope $end
$enddefinitions $end
$comment Show the parameter values. $end
$dumpall
$end
#0
$dumpvars
bx &
1%
0$
b1111 #
0"
0!
$end
#5000
1$
#10000
0$
b111 &
0%
#15000
b110 &
1$
#20000
0$
#25000
b101 &
1$
#30000
0$
#35000
b100 &
1$
#40000
0$
#45000
b11 &
1$
#50000
0$
#55000
1!
b10 &
1"
1$
#60000
0$
#65000
b1 &
1$
#70000
0$
#75000
b0 &
1$
#80000
0$
#85000
b11111111111111111111111111111111 &
1$
