lab1/Q2/circuitC.v
module circuitC (a,b,x);
	input[3:0] a, b;
	output[3:0] x;
	
	assign x = ~a ^ b;
endmodule

lab1/Q2/circuitB.v
module circuitB (a,b,x);
	input[3:0] a, b;
	output[3:0] x;

	assign x = a ^ ~b;
endmodule

lab1/Q2/circuitA.v
module circuitA (a,b,c,x,y);
	input[3:0] a,b;
	input c;
	output[1:0] x;
	output[3:0] y;

    
    // complete the rest of the code
	 assign y = a&b|{1'b0,1'b0,1'b0,c};
	 assign x = {y[3]&y[2],y[1]|y[0]};

endmodule

lab1/Q2/labtest_q2_hardware.v
module labtest_q2_hardware  (a,b,c,d,x);
    input[3:0] a, b, d; // 4-bit wire inputs
	input c;
    output[3:0] x;

    wire[1:0] t1; //2 bit wire - signal for multiplex.
    wire[3:0] t2,t3; //you may use this, but do not have to
    reg[3:0] t5; //you may use this, but do not have to

    circuitA comb1(.a(a),.b(b),.c(c),.x(t1),.y(t2));
    circuitB comb2(.a(d),.b(a),.x(t3));

    // 4 to 1 multiplex - using t1 as a signal.
    always @(t1) begin
        case (t1)
            2'b00 : begin t5<=t2; end
            2'b01 : begin t5<=b; end
            2'b10 : begin t5<=t3; end
            default : begin t5<=d; end
        endcase
    end
    
    circuitC comb3(.a(t5),.b(d),.x(x));
endmodule

lab1/Q2/testbench_labtest2_combinational.v
`timescale 1ns / 1ps
 
module testbench_labtest2_combinational;
 
    integer count;
    
    // ------------------ Specify variables generated by testbench ------------------ 
    reg[3:0] a, b, d;
    reg c;
    
    // ------------------ Specify variables that are watched by testbench ------------------ 
    wire[3:0] x;
    
    labtest_q2_hardware dut(.a(a),.b(b),
                                .c(c),.d(d),
                                .x(x));
 
    // ------------------ Setup inputs ------------------
    // Provide initial values for inputs. The ‘initial’ command
    // is only valid within the testbench.
    // Can use this for all simple testbenches
    initial begin 
        count = 0;
    end
 
    always begin
        #50
        count=count+1;
    end
 
    // Toggle inputs at different rates to cover all input  
    always @(count) begin
        case (count)
            1 : begin a<=4'b0110; b<=4'b1111; c<=1'b0; d<=4'b0100; end 
            2 : begin a<=4'b0010; b<=4'b1101; c<=1'b0; d<=4'b0101; end
            default : begin a<=4'b0000; b<=4'b0000; c<=1'b0;  d<=4'b0000; end 
        endcase
    end

    initial begin

        $dumpfile("testbench_labtest2_combinational.vcd");
        $dumpvars(0, testbench_labtest2_combinational);
        #1000 
        $finish;

	end
 
endmodule

lab1/Q2/testbench_labtest2_combinational.vcd
$date
	Fri Mar 20 14:32:39 2026
$end
$version
	Icarus Verilog
$end
$timescale
	1ps
$end
$scope module testbench_labtest2_combinational $end
$var wire 4 ! x [3:0] $end
$var reg 4 " a [3:0] $end
$var reg 4 # b [3:0] $end
$var reg 1 $ c $end
$var reg 4 % d [3:0] $end
$var integer 32 & count [31:0] $end
$scope module dut $end
$var wire 4 ' a [3:0] $end
$var wire 4 ( b [3:0] $end
$var wire 1 $ c $end
$var wire 4 ) d [3:0] $end
$var wire 4 * x [3:0] $end
$var wire 4 + t3 [3:0] $end
$var wire 4 , t2 [3:0] $end
$var wire 2 - t1 [1:0] $end
$var reg 4 . t5 [3:0] $end
$scope module comb1 $end
$var wire 4 / a [3:0] $end
$var wire 4 0 b [3:0] $end
$var wire 1 $ c $end
$var wire 4 1 y [3:0] $end
$var wire 2 2 x [1:0] $end
$upscope $end
$scope module comb2 $end
$var wire 4 3 a [3:0] $end
$var wire 4 4 b [3:0] $end
$var wire 4 5 x [3:0] $end
$upscope $end
$scope module comb3 $end
$var wire 4 6 a [3:0] $end
$var wire 4 7 b [3:0] $end
$var wire 4 8 x [3:0] $end
$upscope $end
$upscope $end
$upscope $end
$enddefinitions $end
$comment Show the parameter values. $end
$dumpall
$end
#0
$dumpvars
b1111 8
b0 7
b0 6
b1111 5
b0 4
b0 3
b0 2
b0 1
b0 0
b0 /
b0 .
b0 -
b0 ,
b1111 +
b1111 *
b0 )
b0 (
b0 '
b0 &
b0 %
0$
b0 #
b0 "
b1111 !
$end
#50000
b1111 .
b1111 6
b1 -
b1 2
b110 ,
b110 1
b1101 +
b1101 5
b100 !
b100 *
b100 8
b100 %
b100 )
b100 3
b100 7
b1111 #
b1111 (
b1111 0
b110 "
b110 '
b110 /
b110 4
b1 &
#100000
b0 .
b0 6
b0 -
b0 2
b0 ,
b0 1
b1000 +
b1000 5
b1010 !
b1010 *
b1010 8
b101 %
b101 )
b101 3
b101 7
b1101 #
b1101 (
b1101 0
b10 "
b10 '
b10 /
b10 4
b10 &
#150000
b1111 +
b1111 5
b1111 !
b1111 *
b1111 8
b0 %
b0 )
b0 3
b0 7
b0 #
b0 (
b0 0
b0 "
b0 '
b0 /
b0 4
b11 &
#200000
b100 &
#250000
b101 &
#300000
b110 &
#350000
b111 &
#400000
b1000 &
#450000
b1001 &
#500000
b1010 &
#550000
b1011 &
#600000
b1100 &
#650000
b1101 &
#700000
b1110 &
#750000
b1111 &
#800000
b10000 &
#850000
b10001 &
#900000
b10010 &
#950000
b10011 &
#1000000
b10100 &
