lectures/lecture2/iVerilog_files_L2/large_comb_function.v
module large_comb_function (
    input  wire a,
    input  wire b,
    input  wire c,
    input  wire d,
    input  wire e,
    input  wire f,
    output wire x,
    output wire y,
    output wire z
);
    assign x = a & c & e;
    assign y = b | d | f;
    assign z = a ^ b ^ c ^ d ^ e ^ f;
endmodule

lectures/lecture2/iVerilog_files_L2/simple_comb_function2.v
module simple_comb_function2 (a, b, x, y);
	input     		a, b;
	output  reg	    	x, y;
	
	wire[2:0] temp;
	
	assign temp = {a, b};
	
	always @(temp) begin
		case (temp)
			2'b00 : begin x = 1'b0; y = 1'b0; end 
			2'b01 : begin x = 1'b0; y = 1'b1; end 
			2'b11 : begin x = 1'b1; y = 1'b0; end 
			default 	 : begin x = 1'b0; y = 1'b1;end 
		endcase
	end
	
endmodule

lectures/lecture2/iVerilog_files_L2/simple_comb_function.v
module simple_comb_function (a, b, x, y);
	input     		a, b;
	output  reg	    	x, y;
	
	wire[2:0] temp;
	
	assign temp = {a, b};
	
	always @(temp) begin
		case (temp)
			2'b00 : begin x = 1'b0; y = 1'b0; end 
			2'b01 : begin x = 1'b1; y = 1'b0; end 
			2'b11 : begin x = 1'b1; y = 1'b1; end 
			default 	 : begin x = 1'b0; y = 1'b1;end 
		endcase
	end
	
endmodule

lectures/lecture2/iVerilog_files_L2/top_lecture1_example.v
module top_lecture1_example (
    input  wire a1, b1,
    input  wire a2, b2,
    input  wire a3, b3,
    output wire x,
    output wire y,
    output wire z
);

    // Internal wires between blocks
    wire c1_x, c1_y;
    wire c2_x, c2_y;
    wire c3_x, c3_y;

    // Instantiate comb blocks
    simple_comb_function comb1 (
        .a(a1),
        .b(b1),
        .x(c1_x),
        .y(c1_y)
    );

    simple_comb_function comb2 (
        .a(a2),
        .b(b2),
        .x(c2_x),
        .y(c2_y)
    );

    simple_comb_function2 comb3 (
        .a(a3),
        .b(b3),
        .x(c3_x),
        .y(c3_y)
    );

    // Final combinational block
    large_comb_function comb4 (
        .a(c1_x),
        .b(c1_y),
        .c(c2_x),
        .d(c2_y),
        .e(c3_x),
        .f(c3_y),
        .x(x),
        .y(y),
        .z(z)
    );

endmodule

lectures/lecture2/iVerilog_files_L2/tb_top.v
// iverilog -o lecture_example.vvp large_comb_function.v simple_comb_function.v simple_comb_function2.v tb_top.v top_lecture1_example.v
// vvp tb_top.vcd


`timescale 1ns/1ps // 1 unit of time step = 1ns (#5 = wait for 5ns) & 1ps = precision to update gates every picosecond

module tb_top;

    // DUT inputs - assigned within an always block (reg)
    reg a1, b1;
    reg a2, b2;
    reg a3, b3;

    // DUT outputs
    wire x, y, z;

    // Instantiate the Device Under Test (DUT)
    // Instantaites a block of hardware 
    top_lecture1_example dut (
        .a1(a1), .b1(b1),
        .a2(a2), .b2(b2),
        .a3(a3), .b3(b3),
        .x(x), .y(y), .z(z)
    );

    // only for simulation can we create an integer and use initial
    integer i;
    initial begin
        $display(" a1 b1 | a2 b2 | a3 b3 || x y z");
        $display("----------------------------------");
	
        for (i = 0; i < 64; i = i + 1) begin
//            {a1, b1, a2, b2, a3, b3} = i[5:0];
			case (i)
				0 : begin {a1, b1, a2, b2, a3, b3} = 6'b000101; end 
				1 : begin {a1, b1, a2, b2, a3, b3} = 6'b000111; end 
				2 : begin {a1, b1, a2, b2, a3, b3} = 6'b010100; end 
				default 	 : begin {a1, b1, a2, b2, a3, b3} = i[5:0];end // assigned binary value of i e.g. i = 3 = 000011 & i = 65 = 111111
			endcase
            #5;  // allow signals to propagate

            $display("  %0b  %0b |  %0b  %0b |  %0b  %0b || %0b %0b %0b",
                     a1, b1, a2, b2, a3, b3, x, y, z);
        end

        $display("----------------------------------");
        $display("Simulation complete.");
        $finish;
    end

	initial begin

        $dumpfile("tb_top.vcd");

        $dumpvars(0, tb_top);

        #1000 

        $finish;

	end

endmodule

lectures/lecture2/iVerilog_files_L2/tb_top.vcd
$date
	Mon Mar 16 14:04:13 2026
$end
$version
	Icarus Verilog
$end
$timescale
	1ps
$end
$scope module tb_top $end
$var wire 1 ! z $end
$var wire 1 " y $end
$var wire 1 # x $end
$var reg 1 $ a1 $end
$var reg 1 % a2 $end
$var reg 1 & a3 $end
$var reg 1 ' b1 $end
$var reg 1 ( b2 $end
$var reg 1 ) b3 $end
$var integer 32 * i [31:0] $end
$scope module dut $end
$var wire 1 $ a1 $end
$var wire 1 % a2 $end
$var wire 1 & a3 $end
$var wire 1 ' b1 $end
$var wire 1 ( b2 $end
$var wire 1 ) b3 $end
$var wire 1 ! z $end
$var wire 1 " y $end
$var wire 1 # x $end
$var wire 1 + c3_y $end
$var wire 1 , c3_x $end
$var wire 1 - c2_y $end
$var wire 1 . c2_x $end
$var wire 1 / c1_y $end
$var wire 1 0 c1_x $end
$scope module comb1 $end
$var wire 1 $ a $end
$var wire 1 ' b $end
$var wire 3 1 temp [2:0] $end
$var reg 1 0 x $end
$var reg 1 / y $end
$upscope $end
$scope module comb2 $end
$var wire 1 % a $end
$var wire 1 ( b $end
$var wire 3 2 temp [2:0] $end
$var reg 1 . x $end
$var reg 1 - y $end
$upscope $end
$scope module comb3 $end
$var wire 1 & a $end
$var wire 1 ) b $end
$var wire 3 3 temp [2:0] $end
$var reg 1 , x $end
$var reg 1 + y $end
$upscope $end
$scope module comb4 $end
$var wire 1 0 a $end
$var wire 1 / b $end
$var wire 1 . c $end
$var wire 1 - d $end
$var wire 1 , e $end
$var wire 1 + f $end
$var wire 1 # x $end
$var wire 1 " y $end
$var wire 1 ! z $end
$upscope $end
$upscope $end
$upscope $end
$enddefinitions $end
$comment Show the parameter values. $end
$dumpall
$end
#0
$dumpvars
b1 3
b1 2
b0 1
00
0/
1.
0-
0,
1+
b0 *
1)
1(
0'
0&
0%
0$
0#
1"
0!
$end
#5000
0"
0+
1,
b11 3
1&
b1 *
#10000
0!
10
0,
b1 1
1'
0&
b0 3
0)
b10 *
#15000
1!
0#
00
0.
1,
b0 1
0'
b0 2
0(
1&
b11 3
1)
b11 *
#20000
1!
1.
0,
b1 2
1(
0&
b0 3
0)
b100 *
#25000
1"
0!
1+
b1 3
1)
b101 *
#30000
1&
b10 3
0)
b110 *
#35000
0"
0+
1,
b11 3
1)
b111 *
#40000
1"
1!
1-
0.
0,
1%
b10 2
0(
0&
b0 3
0)
b1000 *
#45000
0!
1+
b1 3
1)
b1001 *
#50000
1&
b10 3
0)
b1010 *
#55000
0+
1,
b11 3
1)
b1011 *
#60000
0!
1.
0,
b11 2
1(
0&
b0 3
0)
b1100 *
#65000
1!
1+
b1 3
1)
b1101 *
#70000
1&
b10 3
0)
b1110 *
#75000
0+
1,
b11 3
1)
b1111 *
#80000
0"
1!
10
0-
0.
0,
b1 1
1'
0%
b0 2
0(
0&
b0 3
0)
b10000 *
#85000
1"
0!
1+
b1 3
1)
b10001 *
#90000
1&
b10 3
0)
b10010 *
#95000
0"
0+
1,
b11 3
1)
b10011 *
#100000
0!
1.
0,
b1 2
1(
0&
b0 3
0)
b10100 *
#105000
1"
1!
1+
b1 3
1)
b10101 *
#110000
1&
b10 3
0)
b10110 *
#115000
0"
1#
0+
1,
b11 3
1)
b10111 *
#120000
1"
0!
0#
1-
0.
0,
1%
b10 2
0(
0&
b0 3
0)
b11000 *
#125000
1!
1+
b1 3
1)
b11001 *
#130000
1&
b10 3
0)
b11010 *
#135000
0+
1,
b11 3
1)
b11011 *
#140000
1!
1.
0,
b11 2
1(
0&
b0 3
0)
b11100 *
#145000
0!
1+
b1 3
1)
b11101 *
#150000
1&
b10 3
0)
b11110 *
#155000
1#
0+
1,
b11 3
1)
b11111 *
#160000
1!
0#
1/
00
0-
0.
0,
1$
b10 1
0'
0%
b0 2
0(
0&
b0 3
0)
b100000 *
#165000
0!
1+
b1 3
1)
b100001 *
#170000
1&
b10 3
0)
b100010 *
#175000
0+
1,
b11 3
1)
b100011 *
#180000
0!
1.
0,
b1 2
1(
0&
b0 3
0)
b100100 *
#185000
1!
1+
b1 3
1)
b100101 *
#190000
1&
b10 3
0)
b100110 *
#195000
0+
1,
b11 3
1)
b100111 *
#200000
0!
1-
0.
0,
1%
b10 2
0(
0&
b0 3
0)
b101000 *
#205000
1!
1+
b1 3
1)
b101001 *
#210000
1&
b10 3
0)
b101010 *
#215000
0+
1,
b11 3
1)
b101011 *
#220000
1!
1.
0,
b11 2
1(
0&
b0 3
0)
b101100 *
#225000
0!
1+
b1 3
1)
b101101 *
#230000
1&
b10 3
0)
b101110 *
#235000
0+
1,
b11 3
1)
b101111 *
#240000
0!
10
0-
0.
0,
b11 1
1'
0%
b0 2
0(
0&
b0 3
0)
b110000 *
#245000
1!
1+
b1 3
1)
b110001 *
#250000
1&
b10 3
0)
b110010 *
#255000
0+
1,
b11 3
1)
b110011 *
#260000
1!
1.
0,
b1 2
1(
0&
b0 3
0)
b110100 *
#265000
0!
1+
b1 3
1)
b110101 *
#270000
1&
b10 3
0)
b110110 *
#275000
1#
0+
1,
b11 3
1)
b110111 *
#280000
1!
0#
1-
0.
0,
1%
b10 2
0(
0&
b0 3
0)
b111000 *
#285000
0!
1+
b1 3
1)
b111001 *
#290000
1&
b10 3
0)
b111010 *
#295000
0+
1,
b11 3
1)
b111011 *
#300000
0!
1.
0,
b11 2
1(
0&
b0 3
0)
b111100 *
#305000
1!
1+
b1 3
1)
b111101 *
#310000
1&
b10 3
0)
b111110 *
#315000
1#
0+
1,
b11 3
1)
b111111 *
#320000
b1000000 *
