lab2/Templates/P1/one_bit_2to1mux.v
module one_bit_2to1mux (s,x,y,m);
 
	input s, x, y;
	output m;
	
	assign m = (~(s) & x) | (s & (y));
 
endmodule

lab2/Templates/P3/one_bit_4to1mux.v
module one_bit_4to1mux (s,u,v,w,x,m);
 
	input[1:0] s;
	input u,v,w,x;
	output m;
	
	wire t1, t2;
	
	
	one_bit_2to1mux mux1(.s(s[0]),.x(u),.y(v),.m(t1)); //complete
	//complete other instantiations

	one_bit_2to1mux mux2(.s(s[0]),.x(w),.y(x),.m(t2));

	one_bit_2to1mux mux3(.s(s[1]),.x(t1),.y(t2),.m(m));
	

 
endmodule

lab2/Templates/P3/two_bit_4to1mux.v
module two_bit_4to1mux (s,u,v,w,x,m);
 
	input[1:0] s;
	input[1:0] u, v, w, x;
	output[1:0] m;
	
	one_bit_4to1mux mux1(.s(s), .u(u[0]), .v(v[0]), .w(w[0]), .x(x[0]), .m(m[0])); //complete instantiation
	//complete other instantiations

	one_bit_4to1mux mux2(.s(s), .u(u[1]), .v(v[1]), .w(w[1]), .x(x[1]), .m(m[1]));



endmodule

lab2/Templates/P3/part3_TB.v
`timescale 1ns / 1ps
 
module part3_TB;
 
	// ------------------ Instantiate module ------------------
	// We are instantiating the module mux2, naming it instantiate_mux2.
	// select, input1, input2 are controlled by the testbench, output is 
	// checked  within the testbench
 
	reg [3:0] count;
	reg [1:0] select;
	reg [1:0] input1, input2, input3, input4;
	wire [1:0] output1;
	
	two_bit_4to1mux instantiate_mux4_2bit(.s(select),.u(input1),.v(input2),.w(input3),.x(input4),.m(output1));
 	
	initial begin 
		count = 4'b0000;
	end
	
	always begin
		#50
		count=count+4'b0001;
	end
	
	always @(count) begin
		case (count)
		4'b0000 : begin input1 = 2'b01; input2 = 2'b00; input3 = 2'b00; input4 = 2'b00; select = 2'b00; end
		4'b0001 : begin input1 = 2'b01; input2 = 2'b00; input3 = 2'b00; input4 = 2'b00; select = 2'b01; end
		4'b0010 : begin input1 = 2'b01; input2 = 2'b00; input3 = 2'b00; input4 = 2'b00; select = 2'b10; end
		4'b0011 : begin input1 = 2'b01; input2 = 2'b00; input3 = 2'b00; input4 = 2'b00; select = 2'b11; end
		4'b0100 : begin input1 = 2'b00; input2 = 2'b01; input3 = 2'b00; input4 = 2'b00; select = 2'b00; end
		4'b0101 : begin input1 = 2'b00; input2 = 2'b01; input3 = 2'b00; input4 = 2'b00; select = 2'b01; end
		4'b0110 : begin input1 = 2'b00; input2 = 2'b01; input3 = 2'b00; input4 = 2'b00; select = 2'b10; end
		4'b0111 : begin input1 = 2'b00; input2 = 2'b01; input3 = 2'b00; input4 = 2'b00; select = 2'b11; end
		default : begin input1 = 2'b00; input2 = 2'b00; input3 = 2'b00; input4 = 2'b00; select = 2'b00; end
	endcase
	end

	
	// Dump VCD for GTKWave
    initial begin
        $dumpfile("part3_TB.vcd");
        $dumpvars(0, part3_TB);
        #1000 
        $finish;
	end



 
endmodule

lab2/Templates/P3/part3_TB.vcd
$date
	Fri Mar 27 14:57:08 2026
$end
$version
	Icarus Verilog
$end
$timescale
	1ps
$end
$scope module part3_TB $end
$var wire 2 ! output1 [1:0] $end
$var reg 4 " count [3:0] $end
$var reg 2 # input1 [1:0] $end
$var reg 2 $ input2 [1:0] $end
$var reg 2 % input3 [1:0] $end
$var reg 2 & input4 [1:0] $end
$var reg 2 ' select [1:0] $end
$scope module instantiate_mux4_2bit $end
$var wire 2 ( s [1:0] $end
$var wire 2 ) u [1:0] $end
$var wire 2 * v [1:0] $end
$var wire 2 + w [1:0] $end
$var wire 2 , x [1:0] $end
$var wire 2 - m [1:0] $end
$scope module mux1 $end
$var wire 2 . s [1:0] $end
$var wire 1 / u $end
$var wire 1 0 v $end
$var wire 1 1 w $end
$var wire 1 2 x $end
$var wire 1 3 t2 $end
$var wire 1 4 t1 $end
$var wire 1 5 m $end
$scope module mux1 $end
$var wire 1 4 m $end
$var wire 1 6 s $end
$var wire 1 / x $end
$var wire 1 0 y $end
$upscope $end
$scope module mux2 $end
$var wire 1 3 m $end
$var wire 1 7 s $end
$var wire 1 1 x $end
$var wire 1 2 y $end
$upscope $end
$scope module mux3 $end
$var wire 1 5 m $end
$var wire 1 8 s $end
$var wire 1 4 x $end
$var wire 1 3 y $end
$upscope $end
$upscope $end
$scope module mux2 $end
$var wire 2 9 s [1:0] $end
$var wire 1 : u $end
$var wire 1 ; v $end
$var wire 1 < w $end
$var wire 1 = x $end
$var wire 1 > t2 $end
$var wire 1 ? t1 $end
$var wire 1 @ m $end
$scope module mux1 $end
$var wire 1 ? m $end
$var wire 1 A s $end
$var wire 1 : x $end
$var wire 1 ; y $end
$upscope $end
$scope module mux2 $end
$var wire 1 > m $end
$var wire 1 B s $end
$var wire 1 < x $end
$var wire 1 = y $end
$upscope $end
$scope module mux3 $end
$var wire 1 @ m $end
$var wire 1 C s $end
$var wire 1 ? x $end
$var wire 1 > y $end
$upscope $end
$upscope $end
$upscope $end
$upscope $end
$enddefinitions $end
$comment Show the parameter values. $end
$dumpall
$end
#0
$dumpvars
0C
0B
0A
0@
0?
0>
0=
0<
0;
0:
b0 9
08
07
06
15
14
03
02
01
00
1/
b0 .
b1 -
b0 ,
b0 +
b0 *
b1 )
b0 (
b0 '
b0 &
b0 %
b0 $
b1 #
b0 "
b1 !
$end
#50000
b0 !
b0 -
05
04
16
17
1A
1B
b1 '
b1 (
b1 .
b1 9
b1 "
#100000
14
06
07
18
0A
0B
1C
b10 '
b10 (
b10 .
b10 9
b10 "
#150000
04
16
17
1A
1B
b11 '
b11 (
b11 .
b11 9
b11 "
#200000
06
07
08
0A
0B
0C
10
0/
b0 '
b0 (
b0 .
b0 9
b1 $
b1 *
b0 #
b0 )
b100 "
#250000
b1 !
b1 -
15
14
16
17
1A
1B
b1 '
b1 (
b1 .
b1 9
b101 "
#300000
b0 !
b0 -
05
04
06
07
18
0A
0B
1C
b10 '
b10 (
b10 .
b10 9
b110 "
#350000
14
16
17
1A
1B
b11 '
b11 (
b11 .
b11 9
b111 "
#400000
04
06
07
08
0A
0B
0C
00
b0 '
b0 (
b0 .
b0 9
b0 $
b0 *
b1000 "
#450000
b1001 "
#500000
b1010 "
#550000
b1011 "
#600000
b1100 "
#650000
b1101 "
#700000
b1110 "
#750000
b1111 "
#800000
b1 !
b1 -
15
14
1/
b1 #
b1 )
b0 "
#850000
b0 !
b0 -
05
04
16
17
1A
1B
b1 '
b1 (
b1 .
b1 9
b1 "
#900000
14
06
07
18
0A
0B
1C
b10 '
b10 (
b10 .
b10 9
b10 "
#950000
04
16
17
1A
1B
b11 '
b11 (
b11 .
b11 9
b11 "
#1000000
06
07
08
0A
0B
0C
10
0/
b0 '
b0 (
b0 .
b0 9
b1 $
b1 *
b0 #
b0 )
b100 "
