lab3/L3 P3/decoder_7seg.v
module decoder_7seg(code, decoded_output);

	input[1:0] code;
	output reg[6:0]  decoded_output;
	
 
	//either do with equations: 
	/*
	output[6:0]  decoded_output;
	assign decoded_output[0] = (code[1] & code[0]) | (~code[1] & ~code[0]);
	assign decoded_output[1] = (code[1] & code[0]) | (~code[1] & ~code[0]);
	assign decoded_output[2] = ...;
	*/
	
	// or with case statement:
	/*
	output reg[6:0]  decoded_output;
	always @(code) begin
		case (code)
		4'b0000 : begin decoded_output = 7'b???????; end
		...
		default : begin ... end
	endcase
	end
	*/
	
	always @(code) begin
		case (code)
		2'b00 : begin decoded_output = 7'b0000111; end
		2'b01 : begin decoded_output = 7'b1110000; end
		2'b10 : begin decoded_output = 7'b0011100; end
		default : begin decoded_output = 7'b1100011; end
	endcase
	end



 
endmodule

lab3/L3 P1/lab3_p1_TB.v
`timescale 1ns / 1ps
 
module lab3_p1_TB;
 
	// ------------------ Instantiate module ------------------
	// We are instantiating the module mux2, naming it instantiate_mux2.
	// select, input1, input2 are controlled by the testbench, output is 
	// checked  within the testbench
 
	reg [3:0] count;
	reg [1:0] input_c;
	wire [6:0] output_7seg;
	decoder_7seg instantiate_decoder(.code(input_c),.decoded_output(output_7seg));
 	
	initial begin 
		count = 4'b0000;
	end
	
	always begin
		#50
		count=count+4'b0001;
	end
	
	always @(count) begin
		case (count)
		4'b0000 : begin input_c = 2'b00; end
		4'b0001 : begin input_c = 2'b01; end
		4'b0010 : begin input_c = 2'b10; end
		default : begin input_c = 2'b11; end
	endcase

	end

	// Dump VCD for GTKWave
    initial begin
        $dumpfile("lab3_p1_TB.vcd");
        $dumpvars(0, lab3_p1_TB);
        #1000 
        $finish;
	end

 
endmodule

lab3/L3 P1/lab3_p1_TB.vcd
$date
	Fri Mar 27 13:56:05 2026
$end
$version
	Icarus Verilog
$end
$timescale
	1ps
$end
$scope module lab3_p1_TB $end
$var wire 7 ! output_7seg [6:0] $end
$var reg 4 " count [3:0] $end
$var reg 2 # input_c [1:0] $end
$scope module instantiate_decoder $end
$var wire 2 $ code [1:0] $end
$var reg 7 % decoded_output [6:0] $end
$upscope $end
$upscope $end
$enddefinitions $end
$comment Show the parameter values. $end
$dumpall
$end
#0
$dumpvars
b111 %
b0 $
b0 #
b0 "
b111 !
$end
#50000
b1110000 !
b1110000 %
b1 #
b1 $
b1 "
#100000
b11100 !
b11100 %
b10 #
b10 $
b10 "
#150000
b1100011 !
b1100011 %
b11 #
b11 $
b11 "
#200000
b100 "
#250000
b101 "
#300000
b110 "
#350000
b111 "
#400000
b1000 "
#450000
b1001 "
#500000
b1010 "
#550000
b1011 "
#600000
b1100 "
#650000
b1101 "
#700000
b1110 "
#750000
b1111 "
#800000
b111 !
b111 %
b0 #
b0 $
b0 "
#850000
b1110000 !
b1110000 %
b1 #
b1 $
b1 "
#900000
b11100 !
b11100 %
b10 #
b10 $
b10 "
#950000
b1100011 !
b1100011 %
b11 #
b11 $
b11 "
#1000000
b100 "
